{
    "key": "group_5f859d9b5fc61",
    "title": "Kontaktformular - Footer",
    "fields": [
        {
            "key": "field_5fb4dcd8c9ad9",
            "label": "col12 (copy)",
            "name": "col12_copy",
            "type": "column",
            "instructions": "",
            "required": 0,
            "conditional_logic": 0,
            "wrapper": {
                "width": "",
                "class": "",
                "id": ""
            },
            "column": "1_1",
            "end_column": 0
        },
        {
            "key": "field_5fb4dccfc9ad8",
            "label": "",
            "name": "",
            "type": "message",
            "instructions": "",
            "required": 0,
            "conditional_logic": 0,
            "wrapper": {
                "width": "",
                "class": "",
                "id": ""
            },
            "message": "Kontaktformular | Overskrift + Tekst",
            "new_lines": "wpautop",
            "esc_html": 0
        },
        {
            "key": "field_5f85a0cfe9543",
            "label": "col6",
            "name": "col6",
            "type": "column",
            "instructions": "",
            "required": 0,
            "conditional_logic": 0,
            "wrapper": {
                "width": "",
                "class": "",
                "id": ""
            },
            "column": "1_2",
            "end_column": 0
        },
        {
            "key": "field_5f85a0f4e9545",
            "label": "Billede (Fritlagt selvportræt)",
            "name": "contact_form_footer_img",
            "type": "image",
            "instructions": "",
            "required": 0,
            "conditional_logic": 0,
            "wrapper": {
                "width": "",
                "class": "",
                "id": ""
            },
            "return_format": "array",
            "preview_size": "medium",
            "library": "all",
            "min_width": "",
            "min_height": "",
            "min_size": "",
            "max_width": "",
            "max_height": "",
            "max_size": "",
            "mime_types": ""
        },
        {
            "key": "field_5f85a0e7e9544",
            "label": "col6",
            "name": "col6",
            "type": "column",
            "instructions": "",
            "required": 0,
            "conditional_logic": 0,
            "wrapper": {
                "width": "",
                "class": "",
                "id": ""
            },
            "column": "1_2",
            "end_column": 0
        },
        {
            "key": "field_5f859db1e9542",
            "label": "Overskrift + Tekst",
            "name": "contact_form_footer_title_text",
            "type": "wysiwyg",
            "instructions": "",
            "required": 0,
            "conditional_logic": 0,
            "wrapper": {
                "width": "",
                "class": "",
                "id": ""
            },
            "default_value": "",
            "tabs": "all",
            "toolbar": "full",
            "media_upload": 0,
            "delay": 0
        },
        {
            "key": "field_5fb4dc4126865",
            "label": "col12",
            "name": "col12",
            "type": "column",
            "instructions": "",
            "required": 0,
            "conditional_logic": 0,
            "wrapper": {
                "width": "",
                "class": "",
                "id": ""
            },
            "column": "1_1",
            "end_column": 0
        },
        {
            "key": "field_5fb4dc6426867",
            "label": "",
            "name": "",
            "type": "message",
            "instructions": "",
            "required": 0,
            "conditional_logic": 0,
            "wrapper": {
                "width": "",
                "class": "",
                "id": ""
            },
            "message": "Book-et-møde kontaktformular | Overskrift + Tekst",
            "new_lines": "wpautop",
            "esc_html": 0
        },
        {
            "key": "field_5fb4dc4b26866",
            "label": "Overskrift + Tekst",
            "name": "book_contact_form_footer_title_text",
            "type": "wysiwyg",
            "instructions": "",
            "required": 0,
            "conditional_logic": 0,
            "wrapper": {
                "width": "",
                "class": "",
                "id": ""
            },
            "default_value": "",
            "tabs": "all",
            "toolbar": "full",
            "media_upload": 1,
            "delay": 0
        }
    ],
    "location": [
        [
            {
                "param": "options_page",
                "operator": "==",
                "value": "acf-options-kontaktformular-footer"
            }
        ]
    ],
    "menu_order": 0,
    "position": "normal",
    "style": "default",
    "label_placement": "top",
    "instruction_placement": "label",
    "hide_on_screen": "",
    "active": true,
    "description": "",
    "modified": 1605688548
}